stickydesign/__init__.py
stickydesign/_stickyext.py
stickydesign/endclasses.py
stickydesign/energetics_basic.py
stickydesign/energetics_basic_old.py
stickydesign/energetics_daoe.py
stickydesign/multimodel.py
stickydesign/newparams.py
stickydesign/plots.py
stickydesign/py.typed
stickydesign/stickydesign.py
stickydesign/version.py
stickydesign/params/__init__.py
stickydesign/params/dnastackingbig.csv
stickydesign/stickydesign2/__init__.py
stickydesign/stickydesign2/choosers.py
stickydesign/stickydesign2/design_compat.py
stickydesign/stickydesign2/energetics_basic.py
stickydesign/stickydesign2/energetics_daoe.py
stickydesign/stickydesign2/filters.py
stickydesign/stickydesign2/newparams.py
stickydesign/stickydesign2/plots.py
stickydesign/stickydesign2/seqclasses.py
stickydesign/stickydesign2/util.py
stickydesign-0.9.2.dist-info/METADATA
stickydesign-0.9.2.dist-info/WHEEL
stickydesign-0.9.2.dist-info/top_level.txt
stickydesign-0.9.2.dist-info/RECORD
