Metadata-Version: 2.1
Name: stickydesign
Version: 0.9.2
Summary: StickyDesign DNA Tile Sticky End Package
Author-email: Constantine Evans <const@costi.net>
Project-URL: homepage, https://dna.caltech.edu/StickyDesign
Project-URL: source, https://github.com/DNA-and-Natural-Algorithms-Group/stickydesign
Project-URL: tracker, https://github.com/DNA-and-Natural-Algorithms-Group/stickydesign/issues
Project-URL: download, https://github.com/DNA-and-Natural-Algorithms-Group/stickydesign/releases
Project-URL: changelog, https://github.com/DNA-and-Natural-Algorithms-Group/stickydesign/blob/master/docs/changelog.rst
Requires-Dist: numpy<3.0,>=1.20
Requires-Dist: typing-extensions~=4.0
Provides-Extra: accel
Requires-Dist: stickydesign-accel==0.9.1; extra == "accel"
Provides-Extra: tests
Requires-Dist: pytest-cov; extra == "tests"
Requires-Dist: pytest-benchmark; extra == "tests"
Requires-Dist: pytest; extra == "tests"
Requires-Dist: hypothesis; extra == "tests"
